nts/hardware/analog_sensor/__init__.py
nts/hardware/analog_sensor/interface.py
nts/hardware/analog_sensor/interpolation.py
nts/hardware/analog_sensor/linear.py
nts/hardware/analog_sensor/py.typed
nts/hardware/analog_sensor/version.py
nts_hardware_analog_sensor-1.0.1.dist-info/LICENSE
nts_hardware_analog_sensor-1.0.1.dist-info/METADATA
nts_hardware_analog_sensor-1.0.1.dist-info/WHEEL
nts_hardware_analog_sensor-1.0.1.dist-info/top_level.txt
nts_hardware_analog_sensor-1.0.1.dist-info/RECORD
