Metadata-Version: 2.2
Name: nts.hardware.analog_sensor
Version: 1.0.1
Summary: Analog sensor signal conversion
Author-email: Anton Bondarenko <bond.anton@gmail.com>
License: MIT License
Project-URL: Homepage, https://github.com/bond-anton/nts.hardware.analog_sensor
Project-URL: Bug Tracker, https://github.com/bond-anton/nts.hardware.analog_sensor/issues
Classifier: Programming Language :: Python :: 3
Classifier: License :: OSI Approved :: MIT License
Classifier: Operating System :: OS Independent
Requires-Python: >=3.9
License-File: LICENSE
Requires-Dist: numpy<3.0.0,>=2.0.0
Requires-Dist: scipy<2.0.0,>=1.13.1
Provides-Extra: dev
Provides-Extra: test
Requires-Dist: flake8; extra == "test"
Requires-Dist: pytest; extra == "test"
Requires-Dist: pytest-asyncio; extra == "test"
Provides-Extra: lint
Requires-Dist: pylint; extra == "lint"
